klein_postgres/__init__.py
klein_postgres/connect.py
klein_postgres/postgres.py
klein_postgres-1.1.2.dist-info/LICENSE.txt
klein_postgres-1.1.2.dist-info/METADATA
klein_postgres-1.1.2.dist-info/WHEEL
klein_postgres-1.1.2.dist-info/top_level.txt
klein_postgres-1.1.2.dist-info/zip-safe
klein_postgres-1.1.2.dist-info/RECORD
