Metadata-Version: 2.1
Name: klein-postgres
Version: 1.1.2
Summary: PostgreSQL integration
Home-page: http://github.com/mdcatapult/py-postgres
Author: Medicines Discovery Catapult
Author-email: SoftwareEngineering@md.catapult.org.uk
License: Apache V2
Platform: UNKNOWN
License-File: LICENSE.txt
Requires-Dist: klein-config
Requires-Dist: klein-util
Requires-Dist: psycopg2-binary
